godot_asset_library_client/__init__.py
godot_asset_library_client/__main__.py
godot_asset_library_client/api.py
godot_asset_library_client/cli.py
godot_asset_library_client/config.py
godot_asset_library_client/git.py
godot_asset_library_client/git_test.py
godot_asset_library_client/godot_project_reader.py
godot_asset_library_client/previews.py
godot_asset_library_client/previews_test.py
godot_asset_library_client/testutils.py
godot_asset_library_client/utils.py
godot_asset_library_client-0.5.5.dist-info/licenses/LICENSE
godot_asset_library_client-0.5.5.dist-info/METADATA
godot_asset_library_client-0.5.5.dist-info/WHEEL
godot_asset_library_client-0.5.5.dist-info/entry_points.txt
godot_asset_library_client-0.5.5.dist-info/top_level.txt
godot_asset_library_client-0.5.5.dist-info/RECORD
