Metadata-Version: 2.4
Name: godot-asset-library-client
Version: 0.5.5
Summary: Interaction with the Godot Asset Library
Author-email: David García Garzón <voki@canvoki.net>
License:                     GNU AFFERO GENERAL PUBLIC LICENSE
Project-URL: Homepage, https://vokimon.github.io/godot-asset-library-client
Project-URL: Repository, https://github.com/vokimon/godot-asset-library-client
Project-URL: Changelog, https://github.com/vokimon/godot-asset-library-client/blob/master/CHANGES.md
Keywords: godot,godot asset library,api
Classifier: Development Status :: 5 - Production/Stable
Classifier: Environment :: Console
Classifier: Intended Audience :: Developers
Classifier: Intended Audience :: Science/Research
Classifier: Intended Audience :: Other Audience
Classifier: License :: OSI Approved :: GNU Affero General Public License v3 or later (AGPLv3+)
Classifier: Operating System :: OS Independent
Classifier: Programming Language :: Python :: 3
Classifier: Programming Language :: Python :: 3.10
Classifier: Programming Language :: Python :: 3.11
Classifier: Programming Language :: Python :: 3.12
Classifier: Topic :: System :: Software Distribution
Classifier: Topic :: Games/Entertainment
Requires-Python: >=3.10
License-File: LICENSE
Requires-Dist: yamlns
Requires-Dist: requests
Requires-Dist: pygments
Requires-Dist: typer
Requires-Dist: python-dotenv
Requires-Dist: pytest
Requires-Dist: pytest-cov<4
Dynamic: license-file
